{
  "meta": {
    "code": "2fd0f349-c79c-4c06-9a3d-ca5f93e0f59f",
    "name": "The Dream Eaters CPA 2025",
    "description": "Join the MythosBusters Discord server for the August 2025 Campaign Play-Along of The Dream Eaters!",
    "author": "CPA Organizers",
    "language": "en",
    "external_link": "https://docs.google.com/document/d/15R3Yzpf57OezGwqtemYG4BmTHY5fIEN0gCrl31ooIsc/edit",
    "banner_url": "",
    "types": ["player_cards"],
    "status": "final",
    "date_updated": "2025-09-06T10:59:09.613",
    "generator": "Zoop 3.4, AHLCG plugin 9.8, Strange Eons 3.3.4241"
  },
  "data": {
    "cards": [
      {
        "back_link": "842af37e-2eb0-4c10-8153-2b8535af79fd-back",
        "code": "842af37e-2eb0-4c10-8153-2b8535af79fd",
        "deck_limit": 1,
        "encounter_code": "2fd0f349-c79c-4c06-9a3d-ca5f93e0f59f-the_dream_eaters_cpa_2025",
        "encounter_position": 1,
        "faction_code": "neutral",
        "illustrator": "Tomasz Jedruszek",
        "name": "Dreaming of Sleep",
        "pack_code": "2fd0f349-c79c-4c06-9a3d-ca5f93e0f59f",
        "position": 1,
        "quantity": 1,
        "subname": "Campaign Play-Along",
        "text": "Ultimatum. Accept this contract when assembling investigator decks, and only if you are playing The Dream-Quest.\nWhen you accept this contract, choose [per_investigator] cards. Those cards are added to the card pool for the duration of this campaign.\n<b>Forced</b> - After choosing investigators, flip this card over.",
        "traits": "Contract. Ultimatum. Curse. Dream-Eaters.",
        "type_code": "asset",
        "image_url": "https://eons.arkham.build/842af37e-2eb0-4c10-8153-2b8535af79fd-Front-01%20-%20Dreaming%20of%20Sleep-resolution-300-compressionquality-0.90-bleed-0.0-Front.jpg?cachebust=1755984570644",
        "thumbnail_url": "https://eons.arkham.build/842af37e-2eb0-4c10-8153-2b8535af79fd-Front-thumbnail.png?cachebust=1755984571362"
      },
      {
        "code": "842af37e-2eb0-4c10-8153-2b8535af79fd-back",
        "deck_limit": 1,
        "encounter_code": "2fd0f349-c79c-4c06-9a3d-ca5f93e0f59f-the_dream_eaters_cpa_2025",
        "encounter_position": 1,
        "faction_code": "neutral",
        "hidden": true,
        "name": "Dreaming of Sleep",
        "pack_code": "2fd0f349-c79c-4c06-9a3d-ca5f93e0f59f",
        "position": 1,
        "quantity": 1,
        "subname": "Campaign Play-Along",
        "text": "Choose one investigator to become the bearer of the False Awakening weakness <i>(The Dream-Eaters #233)</i>. For the remainder of this campaign, any time the bearer of the False Awakening weakness leaves the campaign for any reason, choose a new investigator to become the bearer of the False Awakening weakness, and add it to that investigator's deck.\n<b>Forced</b> - If an investigator is instructed to add False Awakening to their deck, the bearer takes 1 mental trauma instead.",
        "traits": "Contract. Ultimatum. Curse. Dream-Eaters.",
        "type_code": "asset",
        "image_url": "https://eons.arkham.build/842af37e-2eb0-4c10-8153-2b8535af79fd-Front-01%20-%20Dreaming%20of%20Sleep-resolution-300-compressionquality-0.90-bleed-0.0-Back.jpg?cachebust=1755984572181",
        "thumbnail_url": "https://eons.arkham.build/842af37e-2eb0-4c10-8153-2b8535af79fd-Front-thumbnail.png?cachebust=1755984571362"
      },
      {
        "code": "e499384b-46a9-4663-9e4e-583ffefd8e08",
        "deck_limit": 1,
        "encounter_code": "2fd0f349-c79c-4c06-9a3d-ca5f93e0f59f-the_dream_eaters_cpa_2025",
        "encounter_position": 3,
        "faction_code": "neutral",
        "illustrator": "Lenka Šimečková",
        "name": "The Cat's Pajamas",
        "pack_code": "2fd0f349-c79c-4c06-9a3d-ca5f93e0f59f",
        "position": 3,
        "quantity": 1,
        "subname": "Campaign Play-Along",
        "text": "Boon. Accept this contract only during deck creation.\nWhen you accept this contract, add Cat Mask and Katarina Sojka to the card pool for the duration of this campaign.\n<b>Forced</b> - When an investigator has <i>\"broken the law of Ulthar\"</i>: Exile all copies of Cat Mask and Katarina Sojka (wherever they are) and remove them from the card pool for the remainder of this campaign.",
        "traits": "Contract. Boon. The Dream-Eaters.",
        "type_code": "asset",
        "image_url": "https://eons.arkham.build/e499384b-46a9-4663-9e4e-583ffefd8e08-Front-03%20-%20The%20Cat's%20Pajamas-resolution-300-compressionquality-0.90-bleed-0.0-Front.jpg?cachebust=1755984566752",
        "thumbnail_url": "https://eons.arkham.build/e499384b-46a9-4663-9e4e-583ffefd8e08-Front-thumbnail.png?cachebust=1755984567393"
      },
      {
        "code": "3a6c43c8-79c9-43d8-bdc5-22a52d89a2b4",
        "deck_limit": 1,
        "encounter_code": "2fd0f349-c79c-4c06-9a3d-ca5f93e0f59f-the_dream_eaters_cpa_2025",
        "encounter_position": 4,
        "faction_code": "neutral",
        "illustrator": "Lenka Šimečková",
        "name": "Fear Made Manifest",
        "pack_code": "2fd0f349-c79c-4c06-9a3d-ca5f93e0f59f",
        "permanent": true,
        "position": 4,
        "quantity": 1,
        "subname": "Campaign Play-Along",
        "text": "Permanent. Limit 1 per campaign. Accept this contract only during deck creation, and only if you are playing The Dream-Quest.\nWhen you accept this contract, choose one card name. That card is added to your card pool for the duration of this campaign.\nThen, add the Your Worst Nightmare weakness to your deck.\nThen, in your Campaign Log, next to \"Evidence of Kadath\", record 1 tally mark.",
        "traits": "Contract. Curse. Dream-Eaters.",
        "type_code": "asset",
        "image_url": "https://eons.arkham.build/3a6c43c8-79c9-43d8-bdc5-22a52d89a2b4-Front-04%20-%20Fear%20Made%20Manifest-resolution-300-compressionquality-0.90-bleed-0.0-Front.jpg?cachebust=1755984569257",
        "thumbnail_url": "https://eons.arkham.build/3a6c43c8-79c9-43d8-bdc5-22a52d89a2b4-Front-thumbnail.png?cachebust=1755984569927"
      },
      {
        "back_link": "726c3e6f-fcbf-4f3e-9b57-c82897a1f27d-back",
        "code": "726c3e6f-fcbf-4f3e-9b57-c82897a1f27d",
        "deck_limit": 1,
        "encounter_code": "2fd0f349-c79c-4c06-9a3d-ca5f93e0f59f-the_dream_eaters_cpa_2025",
        "encounter_position": 2,
        "faction_code": "neutral",
        "illustrator": "Tomasz Jedruszek",
        "name": "Sleeping to Dream",
        "pack_code": "2fd0f349-c79c-4c06-9a3d-ca5f93e0f59f",
        "position": 5,
        "quantity": 1,
        "subname": "Campaign Play-Along",
        "text": "Ultimatum. Accept this contract when assembling investigator decks, and only if you are playing The Web of Dreams.\nWhen you accept this contract, choose [per_investigator] cards. Those cards are added to the card pool for the duration of this campaign.\n<b>Forced</b> - After choosing investigators, flip this card over.",
        "traits": "Contract. Ultimatum. Curse. Dream-Eaters.",
        "type_code": "asset",
        "image_url": "https://eons.arkham.build/726c3e6f-fcbf-4f3e-9b57-c82897a1f27d-Front-02%20-%20Sleeping%20to%20Dream-resolution-300-compressionquality-0.90-bleed-0.0-Front.jpg?cachebust=1755984564451",
        "thumbnail_url": "https://eons.arkham.build/726c3e6f-fcbf-4f3e-9b57-c82897a1f27d-Front-thumbnail.png?cachebust=1755984565218"
      },
      {
        "code": "726c3e6f-fcbf-4f3e-9b57-c82897a1f27d-back",
        "deck_limit": 1,
        "encounter_code": "2fd0f349-c79c-4c06-9a3d-ca5f93e0f59f-the_dream_eaters_cpa_2025",
        "encounter_position": 2,
        "faction_code": "neutral",
        "hidden": true,
        "illustrator": "Tomasz Jedruszek",
        "name": "Sleeping to Dream",
        "pack_code": "2fd0f349-c79c-4c06-9a3d-ca5f93e0f59f",
        "position": 5,
        "quantity": 1,
        "subname": "Campaign Play-Along",
        "text": "Choose one investigator to become the bearer of the False Awakening weakness <i>(The Dream-Eaters #275)</i>. For the remainder of this campaign, any time the bearer of the False Awakening weakness leaves the campaign for any reason, choose a new investigator to become the bearer of the False Awakening weakness, and add it to that investigator's deck.\n<b>Forced</b> - If an investigator is instructed to add False Awakening to their deck, the bearer takes 1 physical trauma instead.",
        "traits": "Contract. Ultimatum. Curse. Dream-Eaters.",
        "type_code": "asset",
        "image_url": "https://eons.arkham.build/726c3e6f-fcbf-4f3e-9b57-c82897a1f27d-Front-02%20-%20Sleeping%20to%20Dream-resolution-300-compressionquality-0.90-bleed-0.0-Back.jpg?cachebust=1755984566036",
        "thumbnail_url": "https://eons.arkham.build/726c3e6f-fcbf-4f3e-9b57-c82897a1f27d-Front-thumbnail.png?cachebust=1755984565218"
      },
      {
        "code": "e122e372-8c4c-4a8d-98df-c710c93b3c36",
        "deck_limit": 1,
        "encounter_code": "2fd0f349-c79c-4c06-9a3d-ca5f93e0f59f-the_dream_eaters_cpa_2025",
        "encounter_position": 5,
        "faction_code": "neutral",
        "illustrator": "Brian Valenzuela",
        "name": "Sleep Paralysis",
        "pack_code": "2fd0f349-c79c-4c06-9a3d-ca5f93e0f59f",
        "permanent": true,
        "position": 5,
        "quantity": 1,
        "subname": "Campaign Play-Along",
        "text": "Permanent. Limit 1 per campaign. Accept this contract only during deck creation, and only if you are playing The Web of Dreams.\nWhen you accept this contract, choose one card name. That card is added to your card pool for the duration of this campaign.\nThen, add the Narcolepsy weakness to your deck.\nWhenever you check the number of tally marks recorded next to \"Steps of the Bridge\" in the Campaign Log, you are considered to have 3 fewer tally marks recorded there.",
        "traits": "Contract. Madness. Dream-Eaters.",
        "type_code": "asset",
        "image_url": "https://eons.arkham.build/e122e372-8c4c-4a8d-98df-c710c93b3c36-Front-05%20-%20Sleep%20Paralysis-resolution-300-compressionquality-0.90-bleed-0.0-Front.jpg?cachebust=1755984567980",
        "thumbnail_url": "https://eons.arkham.build/e122e372-8c4c-4a8d-98df-c710c93b3c36-Front-thumbnail.png?cachebust=1755984568663"
      },
      {
        "code": "d84e16df-dbbc-4ea8-ac59-1b6c8220209d",
        "deck_limit": 1,
        "encounter_code": "2fd0f349-c79c-4c06-9a3d-ca5f93e0f59f-beyond_the_gates_of_sleep_cpa_2025",
        "encounter_position": 1,
        "faction_code": "neutral",
        "illustrator": "Vasily Ermolaev",
        "name": "Whispering Woods",
        "pack_code": "2fd0f349-c79c-4c06-9a3d-ca5f93e0f59f",
        "position": 6,
        "quantity": 1,
        "subname": "Campaign Play-Along",
        "text": "Ultimatum. Accept this contract only during setup for <b>Scenario I-A: Beyond the Gates of Sleep</b>.\n[reaction] When you draw a non-weakness encounter card: Look at cards from the top of the encounter deck until you look at a card with the hidden keyword, add it to your hand, and shuffle the rest into the encounter deck. Then, cancel all effects of the triggering card and discard it. Any investigator may trigger this ability. (Group limit once per game.)\n<b>Forced</b> - After advancing to Act 4a of <b>Scenario I-A: Beyond the Gates of Sleep</b>, search the encounter deck for Ancient Zoog and put it next to the agenda deck. For the remainder of the scenario, its <b>Forced</b> effect is active.",
        "traits": "Contract. Ultimatum. Zoog. Dream-Eaters.",
        "type_code": "asset",
        "image_url": "https://eons.arkham.build/d84e16df-dbbc-4ea8-ac59-1b6c8220209d-Front-06%20-%20Whispering%20Woods-resolution-300-compressionquality-0.90-bleed-0.0-Front.jpg?cachebust=1756546683353",
        "thumbnail_url": "https://eons.arkham.build/d84e16df-dbbc-4ea8-ac59-1b6c8220209d-Front-thumbnail.png?cachebust=1756546683848"
      },
      {
        "code": "d1123cac-d708-44e3-af55-eeef8610dc1e",
        "deck_limit": 1,
        "encounter_code": "2fd0f349-c79c-4c06-9a3d-ca5f93e0f59f-waking_nightmare_cpa_2025",
        "encounter_position": 1,
        "faction_code": "neutral",
        "illustrator": "Diana Franco",
        "name": "Ultimate Infestation",
        "pack_code": "2fd0f349-c79c-4c06-9a3d-ca5f93e0f59f",
        "position": 7,
        "quantity": 1,
        "subname": "Campaign Play-Along",
        "text": "Ultimatum. Accept this contract only during setup for <b>Scenario I-B: Waking Nightmare</b>.\n[reaction] When you would place a swarm card: Look at the top card of your deck. You may place that card as normal. Otherwise, you must place the next card of your deck (without looking at it). Any player may activate this ability. Limit once per round.\n<b>Forced</b> - When you are instructed to assemble the infestation bag, replace the tokens listed with: [skull], [skull], [tablet], [tablet], [tablet], [cultist], [cultist].",
        "traits": "Contract. Ultimatum. Spider. Dream-Eaters.",
        "type_code": "asset",
        "image_url": "https://eons.arkham.build/d1123cac-d708-44e3-af55-eeef8610dc1e-Front-07%20-%20Ultimate%20Infestation-resolution-300-compressionquality-0.90-bleed-0.0-Front.jpg?cachebust=1756546684517",
        "thumbnail_url": "https://eons.arkham.build/d1123cac-d708-44e3-af55-eeef8610dc1e-Front-thumbnail.png?cachebust=1756546684974"
      },
      {
        "back_link": "0d6ba8a8-b12b-4893-b608-9f3a73e758fb-back",
        "code": "0d6ba8a8-b12b-4893-b608-9f3a73e758fb",
        "deck_limit": 1,
        "encounter_code": "2fd0f349-c79c-4c06-9a3d-ca5f93e0f59f-cheshire_cat_cpa_2025",
        "encounter_position": 1,
        "faction_code": "neutral",
        "illustrator": "Nightgrowler",
        "name": "Curiosity Killed the Cat",
        "pack_code": "2fd0f349-c79c-4c06-9a3d-ca5f93e0f59f",
        "position": 8,
        "quantity": 1,
        "subname": "Campaign Play-Along",
        "text": "Ultimatum. Accept this contract only after <b>Interlude I: The Black Cat</b>, and only if <i>you asked for it</i>.\nWhen you accept this contract, choose [per_investigator] cards. Those cards are added to the card pool for the duration of this campaign. Then, each investigator whose deck does not contain a weakness with the [[Madness]] trait must swap a basic weakness in their deck for a random basic weakness with the [[Madness]] trait. Flip this card over for the remainder of the campaign.",
        "traits": "Contract. Ultimatum. Madness. Dream-Eaters.",
        "type_code": "asset",
        "image_url": "https://eons.arkham.build/0d6ba8a8-b12b-4893-b608-9f3a73e758fb-Front-08%20-%20Curiosity%20Killed%20the%20Cat-resolution-300-compressionquality-0.90-bleed-0.0-Front.jpg?cachebust=1757149146540",
        "thumbnail_url": "https://eons.arkham.build/0d6ba8a8-b12b-4893-b608-9f3a73e758fb-Front-thumbnail.png?cachebust=1757149147561"
      },
      {
        "code": "0d6ba8a8-b12b-4893-b608-9f3a73e758fb-back",
        "deck_limit": 1,
        "encounter_code": "2fd0f349-c79c-4c06-9a3d-ca5f93e0f59f-cheshire_cat_cpa_2025",
        "encounter_position": 1,
        "faction_code": "neutral",
        "hidden": true,
        "illustrator": "Reonie Bothma",
        "name": "<i>\"We're all mad here.\"</i>",
        "pack_code": "2fd0f349-c79c-4c06-9a3d-ca5f93e0f59f",
        "position": 8,
        "quantity": 1,
        "subname": "Campaign Play-Along",
        "text": "Ultimatum.\n<b>Forced</b> - When gathering cards during setup, gather The Cheshire Cat from the <i>Cheshire Cat</i> encounter set. Put The Cheshire Cat <i>(Frustrating Feline)</i> into play in the lead investigator's play area.\n<b>Forced</b> - Whenever an investigator draws a [[Madness]] weakness: Flip the Cheshire Cat, then that investigator takes control of The Cheshire Cat, then that investigator may shuffle any number of cards from their hand back into their deck and draw that many cards.",
        "traits": "Contract. Ultimatum. Madness. Dream-Eaters.",
        "type_code": "asset",
        "image_url": "https://eons.arkham.build/0d6ba8a8-b12b-4893-b608-9f3a73e758fb-Front-08%20-%20Curiosity%20Killed%20the%20Cat-resolution-300-compressionquality-0.90-bleed-0.0-Back.jpg?cachebust=1757149148616",
        "thumbnail_url": "https://eons.arkham.build/0d6ba8a8-b12b-4893-b608-9f3a73e758fb-Front-thumbnail.png?cachebust=1757149147561"
      },
      {
        "code": "8e95c8d9-1884-43af-8011-4e54d29ad3b3",
        "deck_limit": 1,
        "encounter_code": "2fd0f349-c79c-4c06-9a3d-ca5f93e0f59f-cheshire_cat_cpa_2025",
        "encounter_position": 2,
        "faction_code": "neutral",
        "illustrator": "Frej Agelli",
        "name": "Adopted by Ulthar",
        "pack_code": "2fd0f349-c79c-4c06-9a3d-ca5f93e0f59f",
        "permanent": true,
        "position": 9,
        "quantity": 1,
        "subname": "Campaign Play-Along",
        "text": "Permanent. Accept this contract only during <b>Interlude I: The Black Cat</b>, and only if <i>the black cat is at your side.</i>\nWhen you accept this contract, add the Pawralysis weakness to your deck for the remainder of the campaign.\nYou have an additional ally slot, which can only be used to hold a [[Creature]] asset.",
        "traits": "Contract. Pact. Dream-Eaters.",
        "type_code": "asset",
        "image_url": "https://eons.arkham.build/8e95c8d9-1884-43af-8011-4e54d29ad3b3-Front-09%20-%20Adopted%20by%20Ulthar-resolution-300-compressionquality-0.90-bleed-0.0-Front.jpg?cachebust=1757149141844",
        "thumbnail_url": "https://eons.arkham.build/8e95c8d9-1884-43af-8011-4e54d29ad3b3-Front-thumbnail.png?cachebust=1757149143074"
      },
      {
        "code": "b0e98a5b-aa1e-4b22-83e0-0dfe6d3b0a76",
        "deck_limit": 1,
        "encounter_code": "2fd0f349-c79c-4c06-9a3d-ca5f93e0f59f-cheshire_cat_cpa_2025",
        "encounter_position": 3,
        "faction_code": "neutral",
        "illustrator": "freyja3120",
        "name": "Pawralysis",
        "pack_code": "2fd0f349-c79c-4c06-9a3d-ca5f93e0f59f",
        "position": 10,
        "quantity": 1,
        "subtype_code": "weakness",
        "text": "<b>Revelation</b> - Attach Pawralysis to a non-weakness asset with the highest printed cost that takes up a hand slot or ally slot. If you cannot, shuffle Pawralysis back into your deck.\nTreat the attached asset as if its printed text box were blank (except for [[Traits]] and forced abilities).\n[action][action]: Pet the damned cat. Discard Pawralysis.",
        "traits": "Creature. Obstacle.",
        "type_code": "treachery",
        "image_url": "https://eons.arkham.build/b0e98a5b-aa1e-4b22-83e0-0dfe6d3b0a76-Front-10%20-%20Pawralysis-resolution-300-compressionquality-0.90-bleed-0.0-Front.jpg?cachebust=1757149144303",
        "thumbnail_url": "https://eons.arkham.build/b0e98a5b-aa1e-4b22-83e0-0dfe6d3b0a76-Front-thumbnail.png?cachebust=1757149145430"
      },
      {
        "back_link": "348fd706-eba6-441d-98cd-efbf23952579-back",
        "code": "348fd706-eba6-441d-98cd-efbf23952579",
        "deck_limit": 1,
        "encounter_code": "2fd0f349-c79c-4c06-9a3d-ca5f93e0f59f-a_thousand_shapes_of_horror_cpa_2025",
        "encounter_position": 1,
        "faction_code": "neutral",
        "illustrator": "Polina Golubeva",
        "name": "Psychic Emanations",
        "pack_code": "2fd0f349-c79c-4c06-9a3d-ca5f93e0f59f",
        "position": 12,
        "quantity": 1,
        "subname": "Campaign Play-Along",
        "text": "Ultimatum. Accept this contract only during setup for <b>Scenario II-B: A Thousand Shapes of Horror</b>.\nReplace the <b>Forced</b> effect on Agenda 2a and 3a of <b>Scenario II-B: A Thousand Shapes of Horror</b> with: \"<b>Forced</b> - At the start of your turn, if The Unnamable is ready, and if it is at your location or you are at a non-[[Graveyard]] location: Test [willpower] (2). Reduce the difficulty of this test by 1 for each location away from The Unnamable you are. If you fail, it attacks you <i>(even if it is not engaged)</i>.\"\n<b>Forced</b> - If an investigator adds The Silver Key to their deck, flip this card over and add it to that investigator's deck.",
        "traits": "Contract. Ultimatum. Dream-Eaters.",
        "type_code": "asset",
        "image_url": "https://eons.arkham.build/348fd706-eba6-441d-98cd-efbf23952579-Front-12%20-%20Psychic%20Emanations-resolution-300-compressionquality-0.90-bleed-0.0-Front.jpg?cachebust=1757149120342",
        "thumbnail_url": "https://eons.arkham.build/348fd706-eba6-441d-98cd-efbf23952579-Front-thumbnail.png?cachebust=1757149121468"
      },
      {
        "code": "348fd706-eba6-441d-98cd-efbf23952579-back",
        "deck_limit": 1,
        "encounter_code": "2fd0f349-c79c-4c06-9a3d-ca5f93e0f59f-a_thousand_shapes_of_horror_cpa_2025",
        "encounter_position": 1,
        "faction_code": "neutral",
        "hidden": true,
        "illustrator": "Oliver Wetter",
        "name": "Psychic Emanations",
        "pack_code": "2fd0f349-c79c-4c06-9a3d-ca5f93e0f59f",
        "permanent": true,
        "position": 12,
        "quantity": 1,
        "subname": "Campaign Play-Along",
        "text": "Permanent. Bearer of The Silver Key only.\nThe Silver Key does not take up an accessory slot.\n[action]: Search your deck and discard pile for The Silver Key and add it to your hand.\n<b>Forced</b> - If another investigator becomes the bearer of The Silver Key, remove this card from your deck and add it to theirs <i>(even if that investigator is taking part in a different campaign)</i>.",
        "traits": "Contract. Ultimatum. Dream-Eaters.",
        "type_code": "asset",
        "image_url": "https://eons.arkham.build/348fd706-eba6-441d-98cd-efbf23952579-Front-12%20-%20Psychic%20Emanations-resolution-300-compressionquality-0.90-bleed-0.0-Back.jpg?cachebust=1757149122492",
        "thumbnail_url": "https://eons.arkham.build/348fd706-eba6-441d-98cd-efbf23952579-Front-thumbnail.png?cachebust=1757149121468"
      }
    ],
    "encounter_sets": [
      {
        "code": "2fd0f349-c79c-4c06-9a3d-ca5f93e0f59f-a_thousand_shapes_of_horror_cpa_2025",
        "name": "A Thousand Shapes of Horror CPA 2025",
        "icon_url": "https://eons.arkham.build/2fd0f349-c79c-4c06-9a3d-ca5f93e0f59f-a_thousand_shapes_of_horror_cpa_2025-encounter-set-icon.png?cachebust=1757149117578"
      },
      {
        "code": "2fd0f349-c79c-4c06-9a3d-ca5f93e0f59f-beyond_the_gates_of_sleep_cpa_2025",
        "name": "Beyond the Gates of Sleep CPA 2025",
        "icon_url": "https://eons.arkham.build/2fd0f349-c79c-4c06-9a3d-ca5f93e0f59f-beyond_the_gates_of_sleep_cpa_2025-encounter-set-icon.png?cachebust=1756546682623"
      },
      {
        "code": "2fd0f349-c79c-4c06-9a3d-ca5f93e0f59f-cheshire_cat_cpa_2025",
        "name": "Cheshire Cat CPA 2025",
        "icon_url": "https://eons.arkham.build/2fd0f349-c79c-4c06-9a3d-ca5f93e0f59f-cheshire_cat_cpa_2025-encounter-set-icon.png?cachebust=1757149118398"
      },
      {
        "code": "2fd0f349-c79c-4c06-9a3d-ca5f93e0f59f-the_dream_eaters_cpa_2025",
        "name": "The Dream Eaters CPA 2025",
        "icon_url": "https://eons.arkham.build/2fd0f349-c79c-4c06-9a3d-ca5f93e0f59f-the_dream_eaters_cpa_2025-encounter-set-icon.png?cachebust=1755984563784"
      },
      {
        "code": "2fd0f349-c79c-4c06-9a3d-ca5f93e0f59f-waking_nightmare_cpa_2025",
        "name": "Waking Nightmare CPA 2025",
        "icon_url": "https://eons.arkham.build/2fd0f349-c79c-4c06-9a3d-ca5f93e0f59f-waking_nightmare_cpa_2025-encounter-set-icon.png?cachebust=1756546682106"
      }
    ],
    "packs": [
      {
        "code": "2fd0f349-c79c-4c06-9a3d-ca5f93e0f59f",
        "name": "The Dream Eaters CPA 2025",
        "date_release": "2025-09-06",
        "icon_url": "https://eons.arkham.build/2fd0f349-c79c-4c06-9a3d-ca5f93e0f59f-collection-icon.png?cachebust=1757149149609"
      }
    ]
  }
}
